encyclopedia_vae/__init__.py
encyclopedia_vae/cli.py
encyclopedia_vae/types_helpers.py
encyclopedia_vae/data/lit_celeba.py
encyclopedia_vae/data/lit_oxfordiitpet.py
encyclopedia_vae/lit_models/lit_vae.py
encyclopedia_vae/losses/__init__.py
encyclopedia_vae/losses/losses.py
encyclopedia_vae/models/__init__.py
encyclopedia_vae/models/base.py
encyclopedia_vae/models/beta_vae.py
encyclopedia_vae/models/betatc_vae.py
encyclopedia_vae/models/cvae.py
encyclopedia_vae/models/vanilla_vae.py
encyclopedia_vae/modules/__init__.py
encyclopedia_vae/modules/decoder.py
encyclopedia_vae/modules/encoder.py
encyclopedia_vae/modules/residual.py
encyclopedia_vae/modules/vectorquantizer.py
encyclopedia_vae-0.2.0.dist-info/METADATA
encyclopedia_vae-0.2.0.dist-info/WHEEL
encyclopedia_vae-0.2.0.dist-info/licenses/LICENSE.md
encyclopedia_vae-0.2.0.dist-info/RECORD
