Metadata-Version: 2.3
Name: encyclopedia-vae
Version: 0.2.0
Summary: Add your description here
Author-email: BaptisteMorisse <bmorisse.pro@proton.me>
License-File: LICENSE.md
Requires-Python: >=3.9
Requires-Dist: einops>=0.8.0
Requires-Dist: jsonargparse[signatures]>=4.28.0
Requires-Dist: lightning[pytorch-extra]>=2.2.4
Requires-Dist: torch>=2.3.0
Requires-Dist: torchsummary>=1.5.1
Provides-Extra: examples
Requires-Dist: torchvision>=0.18.0; extra == 'examples'
